fpd_live_imaging/__init__.py
fpd_live_imaging/acquisition_control_class.py
fpd_live_imaging/communicate_data_dm_class.py
fpd_live_imaging/data_transmitter.py
fpd_live_imaging/live_qt_visualization.py
fpd_live_imaging/process_classes.py
fpd_live_imaging/qt_visualization_annotations.py
fpd_live_imaging/receive_control_communication_class.py
fpd_live_imaging/receive_data_medipix_class.py
fpd_live_imaging/start_live_imaging.py
fpd_live_imaging/start_test_of_data_from_file.py
fpd_live_imaging/temporary_extract_header.py
fpd_live_imaging/testing_tools.py
fpd_live_imaging/sample_scripts/__init__.py
fpd_live_imaging/sample_scripts/run_bf_imaging_test.py
fpd_live_imaging/test_images/__init__.py
fpd_live_imaging/test_images/linux_penguin.npz
fpd_live_imaging/test_images/test_images.py
fpd_live_imaging/tests/__init__.py
fpd_live_imaging/tests/test_acquisition_control.py
fpd_live_imaging/tests/test_internal_data_processes.py
fpd_live_imaging/tests/test_live_data_processes.py
fpd_live_imaging/tests/test_live_qt_visualization.py
fpd_live_imaging/tests/test_medipix_comm.py
fpd_live_imaging/tests/test_running_live_script.py
fpd_live_imaging/tests/test_test_detector.py
fpd_live_imaging-0.0.4.dist-info/DESCRIPTION.rst
fpd_live_imaging-0.0.4.dist-info/METADATA
fpd_live_imaging-0.0.4.dist-info/RECORD
fpd_live_imaging-0.0.4.dist-info/WHEEL
fpd_live_imaging-0.0.4.dist-info/metadata.json
fpd_live_imaging-0.0.4.dist-info/top_level.txt
