Metadata-Version: 2.0
Name: fpd-live-imaging
Version: 0.0.4
Summary: Library for live processing and visualization of STEM data acquired using a fast pixelated detector
Home-page: https://fast_pixelated_detectors.gitlab.io/fpd_live_imaging/
Author: Magnus Nord
Author-email: magnunor@gmail.com
License: GPL v3
Download-URL: https://gitlab.com/fast_pixelated_detectors/fpd_live_imaging/repository/master/archive.tar?ref=0.0.4
Keywords: STEM,visualization,microscopy
Platform: UNKNOWN
Classifier: Development Status :: 3 - Alpha
Classifier: Intended Audience :: Science/Research
Classifier: Programming Language :: Python :: 3
Requires-Dist: h5py
Requires-Dist: numpy
Requires-Dist: psutil
Requires-Dist: pyqt5
Requires-Dist: scipy
